pyc_wheel/__about__.py
pyc_wheel/__init__.py
pyc_wheel/__main__.py
pyc_wheel/_pyc_wheel.py
pyc_wheel/py.typed
pyc_wheel-2.0.11.dist-info/licenses/LICENSE
pyc_wheel-2.0.11.dist-info/METADATA
pyc_wheel-2.0.11.dist-info/WHEEL
pyc_wheel-2.0.11.dist-info/top_level.txt
pyc_wheel-2.0.11.dist-info/zip-safe
pyc_wheel-2.0.11.dist-info/RECORD
