Metadata-Version: 2.4
Name: pyc_wheel
Version: 2.0.11
Summary: Compile all py files in a wheel to pyc files.
Author-email: Adam Karpierz <adam@karpierz.net>, Grant Patten <grant@gpatten.com>
Maintainer-email: Adam Karpierz <adam@karpierz.net>
License-Expression: MIT
Project-URL: Homepage, https://pypi.org/project/pyc-wheel/
Project-URL: Documentation, https://karpierz.github.io/pyc_wheel/
Project-URL: History, https://karpierz.github.io/pyc_wheel/CHANGES.html
Project-URL: Download, https://pypi.org/project/pyc-wheel/
Project-URL: Repository, https://github.com/karpierz/pyc_wheel
Project-URL: Tracker, https://github.com/karpierz/pyc_wheel/issues
Project-URL: Sponsoring, https://www.paypal.com/donate/?hosted_button_id=FX8L7CJUGLW7S
Keywords: pyc_wheel,pycwheel,wheel,pyc,compile
Platform: any
Classifier: Development Status :: 5 - Production/Stable
Classifier: Intended Audience :: Developers
Classifier: Operating System :: OS Independent
Classifier: Natural Language :: Polish
Classifier: Programming Language :: Python
Classifier: Programming Language :: Python :: 3
Classifier: Programming Language :: Python :: 3.10
Classifier: Programming Language :: Python :: 3.11
Classifier: Programming Language :: Python :: 3.12
Classifier: Programming Language :: Python :: 3.13
Classifier: Programming Language :: Python :: 3.14
Classifier: Programming Language :: Python :: 3 :: Only
Classifier: Programming Language :: Python :: Implementation :: CPython
Classifier: Programming Language :: Python :: Implementation :: PyPy
Classifier: Topic :: Software Development :: Libraries :: Python Modules
Classifier: Topic :: Utilities
Classifier: Typing :: Typed
Requires-Python: <4.0.0,>=3.10.0
License-File: LICENSE
Requires-Dist: setuptools>=80.9.0
Requires-Dist: typing-extensions>=4.15.0
Requires-Dist: pkg-about>=2.0.0
Dynamic: license-file
